lumixmaptool/__init__.py
lumixmaptool/copy.py
lumixmaptool-1.0.16.data/scripts/lumixmaptool
lumixmaptool-1.0.16.dist-info/METADATA
lumixmaptool-1.0.16.dist-info/RECORD
lumixmaptool-1.0.16.dist-info/WHEEL
lumixmaptool-1.0.16.dist-info/top_level.txt
