Metadata-Version: 2.1
Name: lumixmaptool
Version: 1.0.16
Summary: Manage GPS information for Panasonic Lumix cameras.
Home-page: https://github.com/MartinThoma/lumixmaptool
Author: Martin Thoma
Author-email: info@martin-thoma.de
Maintainer: Martin Thoma
Maintainer-email: info@martin-thoma.de
License: MIT
Download-URL: https://github.com/MartinThoma/lumixmaptool
Keywords: Lumix,Panasonic,TZ41,Camera,GPS
Platform: Linux
Platform: MacOS X
Platform: Windows
Classifier: Development Status :: 7 - Inactive
Classifier: Environment :: Console
Classifier: Intended Audience :: End Users/Desktop
Classifier: License :: OSI Approved :: MIT License
Classifier: Natural Language :: English
Classifier: Operating System :: POSIX :: Linux
Classifier: Programming Language :: Python
Classifier: Programming Language :: Python :: 2.7
Classifier: Programming Language :: Python :: 3
Classifier: Programming Language :: Python :: 3.3
Classifier: Programming Language :: Python :: 3.4
Classifier: Topic :: Utilities
Requires-Dist: argparse (>=1.2.1)
Requires-Dist: pyparsing (>=2.0.1)
Requires-Dist: pyparsing (>=2.0.1)
